{
	"id": 130155970,
	"name": "Druski Never Clear",
	"creators": [
		"pcwn"
	],
	"verifier": "pcwn",
	"verification": "https://www.youtube.com/watch?v=FtzSlXo-wkQ",
	"percentToQualify": 100,
	"song": " Lost (XVA Remix)",
	"enjoyment": 6,
	"difficulty": 6,
	"records": [

		{
    
            "user": "vipexx",
			"link": "https://youtu.be/uPjQxLmglKA",
			"percent": 100,
			"hz": 360,
			"enjoyment": 0
					},	
		{
			"user": "Zephronox",
			"link": "https://youtu.be/C5lnx1ICAgY",
			"percent": 100,
			"hz": 480,
			"enjoyment": 6

							},	
		{
			"user": "A7Xshin",
			"link": "https://youtu.be/Nx3UC86lE4w",
			"percent": 100,
			"hz": 240,
			"enjoyment": 5
								},	
		{
			"user": "BuzzBuzz",
			"link": "https://youtu.be/TVFbjkhUwKI",
			"percent": 100,
			"hz": 240,
			"enjoyment": 6.5
									},	
		{
			"user": "cookie",
			"link": "https://youtu.be/xhunTafjp24?si=gp-uAVRmy3Rge2uW",
			"percent": 100,
			"hz": 120,
			"enjoyment": 2

		}


	]
}
