{
	"id": 130259418,
	"name": "Sakupen Matteo Redux",
	"creators": [
		"fede"
	],
	"verifier": "vipexx",
	"verification": "https://youtu.be/ShtiV_NCh4s",
	"percentToQualify": 100,
	"song": "mr-jazzman - Iron God: Sakupen Hell Yes RMX",
	"difficulty": 8,
	"enjoyment": 6,
	"records": [

		
		{
			"user": "ZtxGMD",
            "link": "https://youtu.be/a7MWq_MRB_U",
            "percent": 100,
            "hz":240,
		    "enjoyment": 8
		},
		{
			"user": "TostGD",
            "link": "https://youtu.be/kN9sXaoZCqI",
            "percent": 100,
            "hz":240,
		    "enjoyment": 7.5
		},
		{
			"user": "cookie",
            "link": "https://youtu.be/5T87sGFcPr8?si=XLG8qZPoKkKYRW58",
            "percent": 100,
            "hz":120,
		    "enjoyment": 8
				},
		{
			"user": "natej22",
            "link": "https://www.youtube.com/watch?v=N6-lG1O7-oI",
            "percent": 100,
            "hz":240,
		    "enjoyment": 8
		},
		{
			"user": "orangeyL",
            "link": "https://youtu.be/WVV56U1Utoo",
            "percent": 100,
            "hz":240,
		    "enjoyment": 8
		}
  ]
}
